altwalker/__init__.py
altwalker/__main__.py
altwalker/__version__.py
altwalker/_cli.py
altwalker/_prettier.py
altwalker/_utils.py
altwalker/_xml.py
altwalker/cli.py
altwalker/code.py
altwalker/exceptions.py
altwalker/executor.py
altwalker/generate.py
altwalker/graphwalker.py
altwalker/loader.py
altwalker/model.py
altwalker/planner.py
altwalker/reporter.py
altwalker/run.py
altwalker/walker.py
altwalker/data/graphwalker/graphwalker-cli.jar
altwalker/data/models/default.json
altwalker/data/templates/generate/dotnet/class.jinja
altwalker/data/templates/generate/dotnet/code.jinja
altwalker/data/templates/generate/dotnet/csproj.jinja
altwalker/data/templates/generate/dotnet/methods.jinja
altwalker/data/templates/generate/gitignore/base.txt
altwalker/data/templates/generate/gitignore/dotnet.txt
altwalker/data/templates/generate/gitignore/python.txt
altwalker/data/templates/generate/python/class.jinja
altwalker/data/templates/generate/python/code.jinja
altwalker/data/templates/generate/python/methods.jinja
altwalker-0.4.0.dist-info/LICENSE
altwalker-0.4.0.dist-info/METADATA
altwalker-0.4.0.dist-info/WHEEL
altwalker-0.4.0.dist-info/entry_points.txt
altwalker-0.4.0.dist-info/top_level.txt
altwalker-0.4.0.dist-info/RECORD
