Metadata-Version: 2.1
Name: altwalker
Version: 0.4.0
Summary: AltWalker is an open source Model-Based Testing framework that supports running tests written in python3 and .NET/C#. You design your tests as a directed graph and AltWalker generates test cases from your graph (using GraphWalker) and executes them.
Author-email: Altom Consulting <altwalker@altom.com>, Dezmerean Robert <dezmereanrobert@gmail.com>
License: GNU GPLv3
Project-URL: Homepage, https://github.com/altwalker/altwalker
Project-URL: Repository, https://github.com/altwalker/altwalker.git
Project-URL: Bug Tracker, https://github.com/altwalker/altwalker/issues
Keywords: model-based-testing,testing,tests,testing-framework
Classifier: Development Status :: 4 - Beta
Classifier: Development Status :: 5 - Production/Stable
Classifier: Intended Audience :: Developers
Classifier: Intended Audience :: Other Audience
Classifier: Environment :: Console
Classifier: License :: OSI Approved :: GNU General Public License v3 (GPLv3)
Classifier: Programming Language :: C#
Classifier: Programming Language :: Cython
Classifier: Programming Language :: Python :: Implementation
Classifier: Programming Language :: Python :: Implementation :: CPython
Classifier: Programming Language :: Python :: Implementation :: PyPy
Classifier: Programming Language :: Python :: 3 :: Only
Classifier: Programming Language :: Python :: 3.8
Classifier: Programming Language :: Python :: 3.9
Classifier: Programming Language :: Python :: 3.10
Classifier: Programming Language :: Python :: 3.11
Classifier: Operating System :: OS Independent
Classifier: Topic :: Software Development :: Libraries
Classifier: Topic :: Software Development :: Testing
Classifier: Topic :: Software Development :: Testing :: Acceptance
Requires-Python: >=3.8
License-File: LICENSE
Requires-Dist: requests
Requires-Dist: jinja2 ~=3.1
Requires-Dist: psutil ~=5.9
Requires-Dist: click ~=8.1
Requires-Dist: click-help-colors >=0.9.1
Requires-Dist: GitPython
